uuid_v7/__init__.py
uuid_v7/__main__.py
uuid_v7/base.py
uuid_v7/cli.py
uuid_v7-1.0.0.dist-info/LICENSE
uuid_v7-1.0.0.dist-info/METADATA
uuid_v7-1.0.0.dist-info/WHEEL
uuid_v7-1.0.0.dist-info/entry_points.txt
uuid_v7-1.0.0.dist-info/top_level.txt
uuid_v7-1.0.0.dist-info/RECORD
